measure/__init__.py
measure/main.py
str_measure-0.0.3.dist-info/LICENSE
str_measure-0.0.3.dist-info/METADATA
str_measure-0.0.3.dist-info/WHEEL
str_measure-0.0.3.dist-info/top_level.txt
str_measure-0.0.3.dist-info/RECORD
