Metadata-Version: 2.1
Name: str-measure
Version: 0.0.3
Summary: Measure the length of a string.
Home-page: https://github.com/Nemu627/str-measure
Author: Nemu627
Author-email: nemu.otoyume@gmail.com
License: UNKNOWN
Platform: UNKNOWN
Classifier: Programming Language :: Python :: 3.7
Classifier: License :: OSI Approved :: MIT License
Classifier: Operating System :: OS Independent
License-File: LICENSE
